<?xml version="1.0" encoding="UTF-8"?>
<FDSNStationXML xmlns="http://www.fdsn.org/xml/station/1" schemaVersion="1.0">
  <Source>SeisComP3</Source>
  <Sender>ODC</Sender>
  <Created>2015-02-20T10:41:48</Created>
  <Network code="GR" startDate="1976-02-17T00:00:00" restrictedStatus="open">
    <Description>German Regional Seismic Network, BGR Hannover</Description>
    <Station code="BFO" startDate="1991-01-01T00:00:00" restrictedStatus="open">
      <Latitude>48.3311</Latitude>
      <Longitude>8.3303</Longitude>
      <Elevation>589</Elevation>
      <Site>
        <Name>GRSN Station Black Forest Observatory</Name>
        <Country>Germany</Country>
      </Site>
      <CreationDate>1991-01-01T00:00:00</CreationDate>
      <Channel code="BHE" startDate="1991-01-01T00:00:00" endDate="2011-10-19T00:00:00" restrictedStatus="open" locationCode="">
        <Latitude>48.3311</Latitude>
        <Longitude>8.3303</Longitude>
        <Elevation>589</Elevation>
        <Depth>0</Depth>
        <Azimuth>90</Azimuth>
        <Dip>0</Dip>
        <SampleRate>20</SampleRate>
        <SampleRateRatio>
          <NumberSamples>20</NumberSamples>
          <NumberSeconds>1</NumberSeconds>
        </SampleRateRatio>
        <StorageFormat>Steim2</StorageFormat>
        <ClockDrift>0.05</ClockDrift>
        <Sensor resourceId="Sensor#20120723141113.907112.4138">
          <Description>STS2</Description>
        </Sensor>
        <DataLogger resourceId="Datalogger#20120723141113.883481.3977"/>
        <Response>
          <InstrumentSensitivity>
            <Value>598802400</Value>
            <Frequency>1</Frequency>
            <InputUnits>
              <Name>m/s</Name>
            </InputUnits>
            <OutputUnits>
              <Name/>
            </OutputUnits>
          </InstrumentSensitivity>
          <Stage number="1">
            <PolesZeros resourceId="ResponsePAZ#20120723141113.90714.4139" name="GR.BFO..BHE_1991.001_STS2">
              <InputUnits>
                <Name>M/S</Name>
              </InputUnits>
              <OutputUnits>
                <Name>V</Name>
              </OutputUnits>
              <PzTransferFunctionType>LAPLACE (RADIANS/SECOND)</PzTransferFunctionType>
              <NormalizationFactor>1</NormalizationFactor>
              <NormalizationFrequency>1</NormalizationFrequency>
              <Pole number="0">
                <Real>-0.0367429</Real>
                <Imaginary>0.036754</Imaginary>
              </Pole>
              <Pole number="1">
                <Real>-0.0367429</Real>
                <Imaginary>-0.036754</Imaginary>
              </Pole>
              <Zero number="2">
                <Real>0</Real>
                <Imaginary>0</Imaginary>
              </Zero>
              <Zero number="3">
                <Real>0</Real>
                <Imaginary>0</Imaginary>
              </Zero>
            </PolesZeros>
            <StageGain>
              <Value>598802400</Value>
              <Frequency>1</Frequency>
            </StageGain>
          </Stage>
          <Stage number="2">
            <Coefficients>
              <InputUnits>
                <Name>V</Name>
              </InputUnits>
              <OutputUnits>
                <Name>COUNTS</Name>
              </OutputUnits>
              <CfTransferFunctionType>DIGITAL</CfTransferFunctionType>
            </Coefficients>
            <Decimation>
              <InputSampleRate>6.930355364e-310</InputSampleRate>
              <Factor>1</Factor>
              <Offset>0</Offset>
              <Delay>0</Delay>
              <Correction>0</Correction>
            </Decimation>
            <StageGain>
              <Value>1</Value>
              <Frequency>0</Frequency>
            </StageGain>
          </Stage>
        </Response>
      </Channel>
      <Channel code="BHN" startDate="1991-01-01T00:00:00" endDate="2011-10-19T00:00:00" restrictedStatus="open" locationCode="">
        <Latitude>48.3311</Latitude>
        <Longitude>8.3303</Longitude>
        <Elevation>589</Elevation>
        <Depth>0</Depth>
        <Azimuth>0</Azimuth>
        <Dip>0</Dip>
        <SampleRate>20</SampleRate>
        <SampleRateRatio>
          <NumberSamples>20</NumberSamples>
          <NumberSeconds>1</NumberSeconds>
        </SampleRateRatio>
        <StorageFormat>Steim2</StorageFormat>
        <ClockDrift>0.05</ClockDrift>
        <Sensor resourceId="Sensor#20120723141113.906463.4134">
          <Description>STS2</Description>
        </Sensor>
        <DataLogger resourceId="Datalogger#20120723141113.883481.3977"/>
        <Response>
          <InstrumentSensitivity>
            <Value>598802400</Value>
            <Frequency>1</Frequency>
            <InputUnits>
              <Name>m/s</Name>
            </InputUnits>
            <OutputUnits>
              <Name/>
            </OutputUnits>
          </InstrumentSensitivity>
          <Stage number="1">
            <PolesZeros resourceId="ResponsePAZ#20120723141113.906491.4135" name="GR.BFO..BHN_1991.001_STS2">
              <InputUnits>
                <Name>M/S</Name>
              </InputUnits>
              <OutputUnits>
                <Name>V</Name>
              </OutputUnits>
              <PzTransferFunctionType>LAPLACE (RADIANS/SECOND)</PzTransferFunctionType>
              <NormalizationFactor>1</NormalizationFactor>
              <NormalizationFrequency>1</NormalizationFrequency>
              <Pole number="0">
                <Real>-0.0367429</Real>
                <Imaginary>0.036754</Imaginary>
              </Pole>
              <Pole number="1">
                <Real>-0.0367429</Real>
                <Imaginary>-0.036754</Imaginary>
              </Pole>
              <Zero number="2">
                <Real>0</Real>
                <Imaginary>0</Imaginary>
              </Zero>
              <Zero number="3">
                <Real>0</Real>
                <Imaginary>0</Imaginary>
              </Zero>
            </PolesZeros>
            <StageGain>
              <Value>598802400</Value>
              <Frequency>1</Frequency>
            </StageGain>
          </Stage>
          <Stage number="2">
            <Coefficients>
              <InputUnits>
                <Name>V</Name>
              </InputUnits>
              <OutputUnits>
                <Name>COUNTS</Name>
              </OutputUnits>
              <CfTransferFunctionType>DIGITAL</CfTransferFunctionType>
            </Coefficients>
            <Decimation>
              <InputSampleRate>6.930355389e-310</InputSampleRate>
              <Factor>1</Factor>
              <Offset>0</Offset>
              <Delay>0</Delay>
              <Correction>0</Correction>
            </Decimation>
            <StageGain>
              <Value>1</Value>
              <Frequency>0</Frequency>
            </StageGain>
          </Stage>
        </Response>
      </Channel>
      <Channel code="BHZ" startDate="1991-01-01T00:00:00" endDate="2011-10-19T00:00:00" restrictedStatus="open" locationCode="">
        <Latitude>48.3311</Latitude>
        <Longitude>8.3303</Longitude>
        <Elevation>589</Elevation>
        <Depth>0</Depth>
        <Azimuth>0</Azimuth>
        <Dip>-90</Dip>
        <SampleRate>20</SampleRate>
        <SampleRateRatio>
          <NumberSamples>20</NumberSamples>
          <NumberSeconds>1</NumberSeconds>
        </SampleRateRatio>
        <StorageFormat>Steim2</StorageFormat>
        <ClockDrift>0.05</ClockDrift>
        <Sensor resourceId="Sensor#20120723141113.905894.4130">
          <Description>STS2</Description>
        </Sensor>
        <DataLogger resourceId="Datalogger#20120723141113.883481.3977"/>
        <Response>
          <InstrumentSensitivity>
            <Value>598802400</Value>
            <Frequency>1</Frequency>
            <InputUnits>
              <Name>m/s</Name>
            </InputUnits>
            <OutputUnits>
              <Name/>
            </OutputUnits>
          </InstrumentSensitivity>
          <Stage number="1">
            <PolesZeros resourceId="ResponsePAZ#20120723141113.905922.4131" name="GR.BFO..BHZ_1991.001_STS2">
              <InputUnits>
                <Name>M/S</Name>
              </InputUnits>
              <OutputUnits>
                <Name>V</Name>
              </OutputUnits>
              <PzTransferFunctionType>LAPLACE (RADIANS/SECOND)</PzTransferFunctionType>
              <NormalizationFactor>1</NormalizationFactor>
              <NormalizationFrequency>1</NormalizationFrequency>
              <Pole number="0">
                <Real>-0.0367429</Real>
                <Imaginary>0.036754</Imaginary>
              </Pole>
              <Pole number="1">
                <Real>-0.0367429</Real>
                <Imaginary>-0.036754</Imaginary>
              </Pole>
              <Zero number="2">
                <Real>0</Real>
                <Imaginary>0</Imaginary>
              </Zero>
              <Zero number="3">
                <Real>0</Real>
                <Imaginary>0</Imaginary>
              </Zero>
            </PolesZeros>
            <StageGain>
              <Value>598802400</Value>
              <Frequency>1</Frequency>
            </StageGain>
          </Stage>
          <Stage number="2">
            <Coefficients>
              <InputUnits>
                <Name>V</Name>
              </InputUnits>
              <OutputUnits>
                <Name>COUNTS</Name>
              </OutputUnits>
              <CfTransferFunctionType>DIGITAL</CfTransferFunctionType>
            </Coefficients>
            <Decimation>
              <InputSampleRate>6.930355466e-310</InputSampleRate>
              <Factor>1</Factor>
              <Offset>0</Offset>
              <Delay>0</Delay>
              <Correction>0</Correction>
            </Decimation>
            <StageGain>
              <Value>1</Value>
              <Frequency>0</Frequency>
            </StageGain>
          </Stage>
        </Response>
      </Channel>
    </Station>
  </Network>
  <Network code="II" startDate="1980-01-01T00:00:00" restrictedStatus="open">
    <Description>(GSN) Global Seismograph Network (IRIS/IDA)</Description>
    <Station code="BFO" startDate="1996-05-29T00:00:00" restrictedStatus="open">
      <Latitude>48.3319</Latitude>
      <Longitude>8.3311</Longitude>
      <Elevation>589</Elevation>
      <Site>
        <Name>Black Forest Observatory, Schiltach, Germany</Name>
        <Country> Germany</Country>
      </Site>
      <CreationDate>1996-05-29T00:00:00</CreationDate>
      <Channel code="BHE" startDate="2008-01-16T00:00:00" endDate="2012-06-21T14:29:59" restrictedStatus="open" locationCode="00">
        <Latitude>48.3319</Latitude>
        <Longitude>8.3311</Longitude>
        <Elevation>589</Elevation>
        <Depth>0</Depth>
        <Azimuth>90</Azimuth>
        <Dip>0</Dip>
        <SampleRate>20</SampleRate>
        <SampleRateRatio>
          <NumberSamples>20</NumberSamples>
          <NumberSeconds>1</NumberSeconds>
        </SampleRateRatio>
        <StorageFormat>Steim1</StorageFormat>
        <ClockDrift>2.5e-06</ClockDrift>
        <Sensor resourceId="Sensor#20121207101201.213013.1484">
          <Type>VBB</Type>
          <Description>STS-1H</Description>
          <Manufacturer>Streckeisen</Manufacturer>
          <Model>STS-1H</Model>
        </Sensor>
        <DataLogger resourceId="Datalogger#20121207101201.210619.1481">
          <Description>BFO.2008.016.H00</Description>
        </DataLogger>
        <Response>
          <InstrumentSensitivity>
            <Value>3.1632e+10</Value>
            <Frequency>0.05</Frequency>
            <InputUnits>
              <Name>M/S</Name>
            </InputUnits>
            <OutputUnits>
              <Name/>
            </OutputUnits>
          </InstrumentSensitivity>
          <Stage number="1">
            <PolesZeros resourceId="ResponsePAZ#20121207101201.213237.1485" name="BFO.2008.016.HE00">
              <InputUnits>
                <Name>M/S</Name>
              </InputUnits>
              <OutputUnits>
                <Name>V</Name>
              </OutputUnits>
              <PzTransferFunctionType>LAPLACE (HERTZ)</PzTransferFunctionType>
              <NormalizationFactor>100.06</NormalizationFactor>
              <NormalizationFrequency>0.05</NormalizationFrequency>
              <Pole number="0">
                <Real>-6.28</Real>
                <Imaginary>7.78213</Imaginary>
              </Pole>
              <Pole number="1">
                <Real>-6.28</Real>
                <Imaginary>-7.78213</Imaginary>
              </Pole>
              <Pole number="2">
                <Real>-0.002142</Real>
                <Imaginary>0.001753</Imaginary>
              </Pole>
              <Pole number="3">
                <Real>-0.002142</Real>
                <Imaginary>-0.001753</Imaginary>
              </Pole>
              <Zero number="4">
                <Real>0</Real>
                <Imaginary>0</Imaginary>
              </Zero>
              <Zero number="5">
                <Real>0</Real>
                <Imaginary>0</Imaginary>
              </Zero>
            </PolesZeros>
            <StageGain>
              <Value>2539.63</Value>
              <Frequency>0.05</Frequency>
            </StageGain>
          </Stage>
          <Stage number="2">
            <Coefficients>
              <InputUnits>
                <Name>V</Name>
              </InputUnits>
              <OutputUnits>
                <Name>COUNTS</Name>
              </OutputUnits>
              <CfTransferFunctionType>DIGITAL</CfTransferFunctionType>
            </Coefficients>
            <Decimation>
              <InputSampleRate>0</InputSampleRate>
              <Factor>1</Factor>
              <Offset>0</Offset>
              <Delay>0</Delay>
              <Correction>0</Correction>
            </Decimation>
            <StageGain>
              <Value>700143</Value>
              <Frequency>0</Frequency>
            </StageGain>
          </Stage>
        </Response>
      </Channel>
      <Channel code="BHN" startDate="2008-01-16T00:00:00" endDate="2012-06-21T14:29:59" restrictedStatus="open" locationCode="00">
        <Latitude>48.3319</Latitude>
        <Longitude>8.3311</Longitude>
        <Elevation>589</Elevation>
        <Depth>0</Depth>
        <Azimuth>0</Azimuth>
        <Dip>0</Dip>
        <SampleRate>20</SampleRate>
        <SampleRateRatio>
          <NumberSamples>20</NumberSamples>
          <NumberSeconds>1</NumberSeconds>
        </SampleRateRatio>
        <StorageFormat>Steim1</StorageFormat>
        <ClockDrift>2.5e-06</ClockDrift>
        <Sensor resourceId="Sensor#20121207101201.23289.1507">
          <Type>VBB</Type>
          <Description>STS-1H</Description>
          <Manufacturer>Streckeisen</Manufacturer>
          <Model>STS-1H</Model>
        </Sensor>
        <DataLogger resourceId="Datalogger#20121207101201.210619.1481">
          <Description>BFO.2008.016.H00</Description>
        </DataLogger>
        <Response>
          <InstrumentSensitivity>
            <Value>2.39545e+10</Value>
            <Frequency>0.05</Frequency>
            <InputUnits>
              <Name>M/S</Name>
            </InputUnits>
            <OutputUnits>
              <Name/>
            </OutputUnits>
          </InstrumentSensitivity>
          <Stage number="1">
            <PolesZeros resourceId="ResponsePAZ#20121207101201.233133.1508" name="BFO.2008.016.HN00">
              <InputUnits>
                <Name>M/S</Name>
              </InputUnits>
              <OutputUnits>
                <Name>V</Name>
              </OutputUnits>
              <PzTransferFunctionType>LAPLACE (HERTZ)</PzTransferFunctionType>
              <NormalizationFactor>100.076</NormalizationFactor>
              <NormalizationFrequency>0.05</NormalizationFrequency>
              <Pole number="0">
                <Real>-6.29</Real>
                <Imaginary>7.77405</Imaginary>
              </Pole>
              <Pole number="1">
                <Real>-6.29</Real>
                <Imaginary>-7.77405</Imaginary>
              </Pole>
              <Pole number="2">
                <Real>-0.002157</Real>
                <Imaginary>0.001657</Imaginary>
              </Pole>
              <Pole number="3">
                <Real>-0.002157</Real>
                <Imaginary>-0.001657</Imaginary>
              </Pole>
              <Zero number="4">
                <Real>0</Real>
                <Imaginary>0</Imaginary>
              </Zero>
              <Zero number="5">
                <Real>0</Real>
                <Imaginary>0</Imaginary>
              </Zero>
            </PolesZeros>
            <StageGain>
              <Value>2572.99</Value>
              <Frequency>0.05</Frequency>
            </StageGain>
          </Stage>
          <Stage number="2">
            <Coefficients>
              <InputUnits>
                <Name>V</Name>
              </InputUnits>
              <OutputUnits>
                <Name>COUNTS</Name>
              </OutputUnits>
              <CfTransferFunctionType>DIGITAL</CfTransferFunctionType>
            </Coefficients>
            <Decimation>
              <InputSampleRate>0</InputSampleRate>
              <Factor>1</Factor>
              <Offset>0</Offset>
              <Delay>0</Delay>
              <Correction>0</Correction>
            </Decimation>
            <StageGain>
              <Value>700143</Value>
              <Frequency>0</Frequency>
            </StageGain>
          </Stage>
        </Response>
      </Channel>
      <Channel code="BHZ" startDate="2008-01-16T00:00:00" endDate="2012-06-21T14:29:59" restrictedStatus="open" locationCode="00">
        <Latitude>48.3319</Latitude>
        <Longitude>8.3311</Longitude>
        <Elevation>589</Elevation>
        <Depth>0</Depth>
        <Azimuth>0</Azimuth>
        <Dip>-90</Dip>
        <SampleRate>20</SampleRate>
        <SampleRateRatio>
          <NumberSamples>20</NumberSamples>
          <NumberSeconds>1</NumberSeconds>
        </SampleRateRatio>
        <StorageFormat>Steim1</StorageFormat>
        <ClockDrift>2.5e-06</ClockDrift>
        <Sensor resourceId="Sensor#20121207101201.250929.1527">
          <Type>VBB</Type>
          <Description>STS-1V</Description>
          <Manufacturer>Streckeisen</Manufacturer>
          <Model>STS-1V</Model>
        </Sensor>
        <DataLogger resourceId="Datalogger#20121207101201.210619.1481">
          <Description>BFO.2008.016.H00</Description>
        </DataLogger>
        <Response>
          <InstrumentSensitivity>
            <Value>2.27009e+10</Value>
            <Frequency>0.05</Frequency>
            <InputUnits>
              <Name>M/S</Name>
            </InputUnits>
            <OutputUnits>
              <Name/>
            </OutputUnits>
          </InstrumentSensitivity>
          <Stage number="1">
            <PolesZeros resourceId="ResponsePAZ#20121207101201.251156.1528" name="BFO.2008.016.HZ00">
              <InputUnits>
                <Name>M/S</Name>
              </InputUnits>
              <OutputUnits>
                <Name>V</Name>
              </OutputUnits>
              <PzTransferFunctionType>LAPLACE (HERTZ)</PzTransferFunctionType>
              <NormalizationFactor>96.1326</NormalizationFactor>
              <NormalizationFrequency>0.05</NormalizationFrequency>
              <Pole number="0">
                <Real>-6.27451</Real>
                <Imaginary>7.53309</Imaginary>
              </Pole>
              <Pole number="1">
                <Real>-6.27451</Real>
                <Imaginary>-7.53309</Imaginary>
              </Pole>
              <Pole number="2">
                <Real>-0.002003</Real>
                <Imaginary>0.001898</Imaginary>
              </Pole>
              <Pole number="3">
                <Real>-0.002003</Real>
                <Imaginary>-0.001898</Imaginary>
              </Pole>
              <Zero number="4">
                <Real>0</Real>
                <Imaginary>0</Imaginary>
              </Zero>
              <Zero number="5">
                <Real>0</Real>
                <Imaginary>0</Imaginary>
              </Zero>
            </PolesZeros>
            <StageGain>
              <Value>2419.66</Value>
              <Frequency>0.05</Frequency>
            </StageGain>
          </Stage>
          <Stage number="2">
            <Coefficients>
              <InputUnits>
                <Name>V</Name>
              </InputUnits>
              <OutputUnits>
                <Name>COUNTS</Name>
              </OutputUnits>
              <CfTransferFunctionType>DIGITAL</CfTransferFunctionType>
            </Coefficients>
            <Decimation>
              <InputSampleRate>0</InputSampleRate>
              <Factor>1</Factor>
              <Offset>0</Offset>
              <Delay>0</Delay>
              <Correction>0</Correction>
            </Decimation>
            <StageGain>
              <Value>700143</Value>
              <Frequency>0</Frequency>
            </StageGain>
          </Stage>
        </Response>
      </Channel>
    </Station>
  </Network>
</FDSNStationXML>
